videotello/__init__.py
videotello/tello.py
videotello-0.0.2b0.dist-info/LICENSE
videotello-0.0.2b0.dist-info/METADATA
videotello-0.0.2b0.dist-info/WHEEL
videotello-0.0.2b0.dist-info/top_level.txt
videotello-0.0.2b0.dist-info/RECORD
