Metadata-Version: 2.1
Name: videotello
Version: 0.0.2b0
Summary: An easy framework to support DJI Tello Video Recording in Python 3
Home-page: https://github.com/Piphi5/videotello
Author: Matteo Kimura
Author-email: mateus.sakata@gmail.com
License: UNKNOWN
Platform: UNKNOWN
Classifier: Programming Language :: Python :: 3
Classifier: License :: OSI Approved :: MIT License
Classifier: Operating System :: OS Independent
License-File: LICENSE
Requires-Dist: djitellopy
